{
    "name": "Category",
    "fields": [
        {
            "fieldName": "name",
            "fieldType": "String"
        }
    ],
    "relationships": [
        {
            "relationshipType": "one-to-many",
            "otherEntityName": "product",
            "otherEntityRelationshipName": "category",
            "relationshipName": "product"
        }
    ],
    "changelogDate": "20200420185300",
    "entityTableName": "category",
    "dto": "no",
    "pagination": "pagination",
    "service": "serviceImpl",
    "jpaMetamodelFiltering": false,
    "fluentMethods": true,
    "readOnly": false,
    "embedded": false,
    "clientRootFolder": "",
    "applications": "*"
}